briefer/__init__.py
briefer/main.py
briefer-0.0.14.dist-info/LICENSE
briefer-0.0.14.dist-info/METADATA
briefer-0.0.14.dist-info/WHEEL
briefer-0.0.14.dist-info/entry_points.txt
briefer-0.0.14.dist-info/top_level.txt
briefer-0.0.14.dist-info/RECORD
