Metadata-Version: 2.1
Name: briefer
Version: 0.0.14
Summary: Python notebooks and dashboards in a single place. Create powerful and flexible dashboards using code, or build beautiful Notion-like notebooks and share them with your team.
License: GNU AFFERO GENERAL PUBLIC LICENSE
Project-URL: Homepage, https://briefer.cloud
Project-URL: Documentation, https://github.com/briefercloud/briefer/README.md
Project-URL: Repository, https://github.com/briefercloud/briefer
Requires-Python: >=3.7
License-File: LICENSE
Requires-Dist: docker
Requires-Dist: requests
